mindm_mcp/__init__.py
mindm_mcp/server.py
mindm_mcp-0.0.2.3.dist-info/licenses/LICENSE
mindm_mcp-0.0.2.3.dist-info/METADATA
mindm_mcp-0.0.2.3.dist-info/WHEEL
mindm_mcp-0.0.2.3.dist-info/entry_points.txt
mindm_mcp-0.0.2.3.dist-info/top_level.txt
mindm_mcp-0.0.2.3.dist-info/RECORD
