Metadata-Version: 2.4
Name: mindm_mcp
Version: 0.0.2.3
Summary: Model Context Protocol (MCP) server for the mindm library, enabling AI assistants like Claude to interact with MindManager.
Author: Robert Zaufall
Project-URL: Homepage, https://github.com/robertZaufall/mindm-mcp
Project-URL: Bug Tracker, https://github.com/robertZaufall/mindm-mcp/issues
Classifier: Programming Language :: Python :: 3
Classifier: License :: OSI Approved :: MIT License
Classifier: Operating System :: Microsoft :: Windows
Classifier: Operating System :: MacOS :: MacOS X
Requires-Python: >=3.12
License-File: LICENSE
Requires-Dist: mindm>=0.0.5.3
Requires-Dist: uvicorn>=0.22.0
Requires-Dist: aiohttp>=3.8.4
Requires-Dist: pydantic>=1.10.7
Requires-Dist: websockets>=10.4
Requires-Dist: fastmcp>=0.4.1
Requires-Dist: mcp[cli]>=1.6.0
Requires-Dist: build>=1.2.2.post1
Dynamic: license-file
